gt4py/__about__.py
gt4py/__init__.py
gt4py/py.typed
gt4py/_core/__init__.py
gt4py/_core/definitions.py
gt4py/_core/filecache.py
gt4py/_core/locking.py
gt4py/_core/ndarray_utils.py
gt4py/cartesian/__externals__.py
gt4py/cartesian/__gtscript__.py
gt4py/cartesian/__init__.py
gt4py/cartesian/caching.py
gt4py/cartesian/config.py
gt4py/cartesian/definitions.py
gt4py/cartesian/gt_cache_manager.py
gt4py/cartesian/gtscript.py
gt4py/cartesian/gtscript_imports.py
gt4py/cartesian/lazy_stencil.py
gt4py/cartesian/loader.py
gt4py/cartesian/stencil_builder.py
gt4py/cartesian/stencil_object.py
gt4py/cartesian/type_hints.py
gt4py/cartesian/backend/__init__.py
gt4py/cartesian/backend/base.py
gt4py/cartesian/backend/dace_backend.py
gt4py/cartesian/backend/dace_lazy_stencil.py
gt4py/cartesian/backend/dace_stencil_object.py
gt4py/cartesian/backend/debug_backend.py
gt4py/cartesian/backend/gtc_common.py
gt4py/cartesian/backend/gtcpp_backend.py
gt4py/cartesian/backend/module_generator.py
gt4py/cartesian/backend/numpy_backend.py
gt4py/cartesian/backend/pyext_builder.py
gt4py/cartesian/backend/python_common.py
gt4py/cartesian/backend/templates/__init__.py
gt4py/cartesian/backend/templates/stencil_module.py.in
gt4py/cartesian/frontend/__init__.py
gt4py/cartesian/frontend/base.py
gt4py/cartesian/frontend/defir_to_gtir.py
gt4py/cartesian/frontend/exceptions.py
gt4py/cartesian/frontend/gtscript_frontend.py
gt4py/cartesian/frontend/node_util.py
gt4py/cartesian/frontend/nodes.py
gt4py/cartesian/gtc/__init__.py
gt4py/cartesian/gtc/common.py
gt4py/cartesian/gtc/definitions.py
gt4py/cartesian/gtc/gtir.py
gt4py/cartesian/gtc/gtir_to_oir.py
gt4py/cartesian/gtc/oir.py
gt4py/cartesian/gtc/ufuncs.py
gt4py/cartesian/gtc/utils.py
gt4py/cartesian/gtc/dace/__init__.py
gt4py/cartesian/gtc/dace/oir_to_tasklet.py
gt4py/cartesian/gtc/dace/oir_to_treeir.py
gt4py/cartesian/gtc/dace/treeir.py
gt4py/cartesian/gtc/dace/treeir_to_stree.py
gt4py/cartesian/gtc/dace/utils.py
gt4py/cartesian/gtc/dace/passes/__init__.py
gt4py-1.1.3.dist-info/licenses/LICENSE
gt4py-1.1.3.dist-info/METADATA
gt4py-1.1.3.dist-info/WHEEL
gt4py-1.1.3.dist-info/top_level.txt
gt4py-1.1.3.dist-info/RECORD
