Metadata-Version: 2.4
Name: gt4py
Version: 1.1.3
Summary: Python library for generating high-performance implementations of stencil kernels for weather and climate modeling from a domain-specific language (DSL)
Author-email: ETH Zurich <gridtools@cscs.ch>
License-Expression: BSD-3-Clause
Project-URL: Documentation, https://gridtools.github.io/gt4py
Project-URL: Homepage, https://gridtools.github.io/
Project-URL: Repository, https://github.com/GridTools/gt4py
Keywords: gridtools,stencil,weather,climate,performance,portable,hpc
Platform: Linux
Platform: Mac
Classifier: Development Status :: 4 - Beta
Classifier: Environment :: Console
Classifier: Environment :: GPU :: NVIDIA CUDA
Classifier: Intended Audience :: Science/Research
Classifier: Operating System :: POSIX
Classifier: Programming Language :: Python
Classifier: Programming Language :: Python :: 3.10
Classifier: Programming Language :: Python :: 3.11
Classifier: Programming Language :: Python :: 3.12
Classifier: Programming Language :: Python :: 3.13
Classifier: Programming Language :: Python :: 3.14
Classifier: Programming Language :: Python :: Implementation :: CPython
Classifier: Topic :: Scientific/Engineering :: Atmospheric Science
Classifier: Topic :: Scientific/Engineering :: Mathematics
Classifier: Topic :: Scientific/Engineering :: Physics
Requires-Python: !=3.13.10,!=3.14.1,<3.15,>=3.10
License-File: LICENSE
Requires-Dist: attrs>=21.3
Requires-Dist: black>=25.11
Requires-Dist: boltons>=20.1
Requires-Dist: cached-property>=1.5.1
Requires-Dist: click>=8.0.0
Requires-Dist: cmake>=3.22
Requires-Dist: cytoolz>=1.0.1
Requires-Dist: deepdiff>=8.1.0
Requires-Dist: devtools>=0.6
Requires-Dist: factory-boy>=3.3.3
Requires-Dist: filelock>=3.18.0
Requires-Dist: frozendict>=2.3
Requires-Dist: gridtools-cpp==2.*,>=2.3.9
Requires-Dist: jinja2>=3.0.0
Requires-Dist: lark>=1.1.2
Requires-Dist: mako>=1.3
Requires-Dist: nanobind>=1.9.0
Requires-Dist: ninja>=1.11
Requires-Dist: numpy>=1.26.4
Requires-Dist: packaging>=20.0
Requires-Dist: pybind11>=2.10.1
Requires-Dist: setuptools>=77.0.3
Requires-Dist: tabulate>=0.8.10
Requires-Dist: toolz>=0.12.1
Requires-Dist: typing-extensions>=4.12.0
Requires-Dist: versioningit>=3.1.1
Requires-Dist: xxhash>=3.5.0
Provides-Extra: cartesian
Requires-Dist: gt4py[jax,standard,testing]; extra == "cartesian"
Provides-Extra: cuda11
Requires-Dist: cupy-cuda11x>=12.0; extra == "cuda11"
Provides-Extra: cuda12
Requires-Dist: cupy-cuda12x>=12.0; extra == "cuda12"
Provides-Extra: jax
Requires-Dist: jax>=0.4.26; extra == "jax"
Provides-Extra: jax-cuda12
Requires-Dist: jax[cuda12_local]>=0.4.26; extra == "jax-cuda12"
Requires-Dist: gt4py[cuda12]; extra == "jax-cuda12"
Provides-Extra: next
Requires-Dist: gt4py[jax,standard,testing]; extra == "next"
Provides-Extra: rocm4-3
Requires-Dist: cupy-rocm-4-3>=13.3.0; extra == "rocm4-3"
Provides-Extra: rocm5-0
Requires-Dist: cupy-rocm-5-0>=13.3.0; extra == "rocm5-0"
Provides-Extra: rocm6-0
Requires-Dist: cupy>=13.4.1; extra == "rocm6-0"
Provides-Extra: standard
Requires-Dist: clang-format>=18.1; extra == "standard"
Requires-Dist: scipy>=1.14.1; python_version < "3.11" and extra == "standard"
Requires-Dist: scipy>=1.16.1; python_version >= "3.11" and extra == "standard"
Provides-Extra: testing
Requires-Dist: hypothesis>=6.93; extra == "testing"
Requires-Dist: pytest>=7.0; extra == "testing"
Dynamic: license-file
